Workbook

Sheet README
A1: V5 Logistics – Transportation Cost Model
A2: Bhiwandi vs Proposed Kolhapur Mini-Hub | Modelled scenario analysis | Prepared by Mahir Valani, Intern
A4: Colour legend: BLUE on light blue = supplied source input (editable). BLUE on yellow = analyst/user scenario assumption (editable). BLACK on grey = formula.
A5: Sheets: Inputs | Route_Model | Components | Hub_Sensitivity | Dashboard | Notes.
A6: All figures are MODELLED using supplied assumptions (80 machines per route, 20 machines per 6-tyre vehicle). They are not actual V5 shipment volumes, expenditure or verified savings.
A7: Savings are modelled GROSS transportation-cost savings. Incremental Kolhapur hub costs are not available; the Hub_Sensitivity sheet uses editable illustrative values.
A8: Net benefit % is a percentage of baseline transportation cost, not a profit margin.
A9: Chennai primary cost per vehicle (₹48,600 / ₹38,000) are supplied working figures pending confirmation against the original quotation. No per-km rate has been derived.
A10: Audit: the brief's combined reduction of 14.79% recalculates to 14.78% (₹2,60,560 ÷ ₹17,62,400 = 14.784%). All rupee totals reconcile exactly.

Sheet Inputs
A1: Inputs – supplied assumptions (editable)
A2: Edit blue cells only. Everything else recalculates.
A3: Parameter | B3: Goa | C3: Bengaluru | D3: Chennai | E3: Note
A4: Machines modelled per route | B4: 80 | C4: 80 | D4: 80 | E4: Modelling basis, NOT actual shipment volume
A5: Machines per vehicle | B5: 20 | E5: 6-tyre vehicle; 10 t nominal; max planning capacity 20 machines (single value, cell B5)
A6: Bhiwandi primary distance (km) | B6: 600 | C6: 1000 | D6: n/a | E6: Cost distance; may differ from transit-time report
A7: Bhiwandi rate (₹/km) | B7: 40 | C7: 38 | D7: n/a
A8: Kolhapur primary distance (km) | B8: 250 | C8: 630 | D8: n/a | E8: Cost distance; Goa 250 km vs 223 km in transit-time report
A9: Kolhapur rate (₹/km) | B9: 44 | C9: 42 | D9: n/a
A10: Chennai: Bhiwandi primary cost per vehicle (₹) | B10: n/a | C10: n/a | D10: 48600 | E10: Supplied working figure – confirm against quotation
A11: Chennai: Kolhapur primary cost per vehicle (₹) | B11: n/a | C11: n/a | D11: 38000 | E11: Supplied working figure – confirm; equals Bengaluru Bhiwandi vehicle cost, verify not a transcription slip
A12: Secondary transport per machine – Bhiwandi (₹) | B12: 3000 | C12: 3000 | D12: 3000 | E12: Supplied; identical across routes
A13: Secondary transport per machine – Kolhapur (₹) | B13: 2500 | C13: 2500 | D13: 2500 | E13: Supplied; identical across routes
A14: Last-mile per machine – Bhiwandi (₹) | B14: 2500 | C14: 2500 | D14: 2500 | E14: Supplied
A15: Last-mile per machine – Kolhapur (₹) | B15: 2500 | C15: 2500 | D15: 2500 | E15: Supplied; unchanged between scenarios

Sheet Route_Model
A1: Route-level cost model
A2: Per-machine and 80-machine comparison. Same machine quantity in both scenarios.
A3: Line | B3: Goa | C3: Bengaluru | D3: Chennai | E3: Total (3 routes)
A4: Primary cost per vehicle – Bhiwandi (₹) | B4: =Inputs!B6*Inputs!B7 -> 24000 | C4: =Inputs!C6*Inputs!C7 -> 38000 | D4: =Inputs!D10 -> 48600
A5: Primary cost per vehicle – Kolhapur (₹) | B5: =Inputs!B8*Inputs!B9 -> 11000 | C5: =Inputs!C8*Inputs!C9 -> 26460 | D5: =Inputs!D11 -> 38000
A6: Primary cost per machine – Bhiwandi (₹) | B6: =B4/Inputs!$B$5 -> 1200 | C6: =C4/Inputs!$B$5 -> 1900 | D6: =D4/Inputs!$B$5 -> 2430
A7: Primary cost per machine – Kolhapur (₹) | B7: =B5/Inputs!$B$5 -> 550 | C7: =C5/Inputs!$B$5 -> 1323 | D7: =D5/Inputs!$B$5 -> 1900
A8: Secondary per machine – Bhiwandi (₹) | B8: =Inputs!B12 -> 3000 | C8: =Inputs!C12 -> 3000 | D8: =Inputs!D12 -> 3000
A9: Secondary per machine – Kolhapur (₹) | B9: =Inputs!B13 -> 2500 | C9: =Inputs!C13 -> 2500 | D9: =Inputs!D13 -> 2500
A10: Last-mile per machine – Bhiwandi (₹) | B10: =Inputs!B14 -> 2500 | C10: =Inputs!C14 -> 2500 | D10: =Inputs!D14 -> 2500
A11: Last-mile per machine – Kolhapur (₹) | B11: =Inputs!B15 -> 2500 | C11: =Inputs!C15 -> 2500 | D11: =Inputs!D15 -> 2500
A12: Total cost per machine – Bhiwandi (₹) | B12: =B6+B8+B10 -> 6700 | C12: =C6+C8+C10 -> 7400 | D12: =D6+D8+D10 -> 7930 | E12: n/a
A13: Total cost per machine – Kolhapur (₹) | B13: =B7+B9+B11 -> 5550 | C13: =C7+C9+C11 -> 6323 | D13: =D7+D9+D11 -> 6900 | E13: n/a
A14: Machines modelled | B14: =Inputs!B4 -> 80 | C14: =Inputs!C4 -> 80 | D14: =Inputs!D4 -> 80 | E14: =SUM(B14:D14) -> 240
A15: Equivalent vehicle loads | B15: =B14/Inputs!$B$5 -> 4 | C15: =C14/Inputs!$B$5 -> 4 | D15: =D14/Inputs!$B$5 -> 4 | E15: =SUM(B15:D15) -> 12
A16: Total cost – Bhiwandi scenario (₹) | B16: =B12*B14 -> 536000 | C16: =C12*C14 -> 592000 | D16: =D12*D14 -> 634400 | E16: =SUM(B16:D16) -> 1762400
A17: Total cost – Kolhapur scenario (₹) | B17: =B13*B14 -> 444000 | C17: =C13*C14 -> 505840 | D17: =D13*D14 -> 552000 | E17: =SUM(B17:D17) -> 1501840
A18: Modelled gross saving (₹) | B18: =B16-B17 -> 92000 | C18: =C16-C17 -> 86160 | D18: =D16-D17 -> 82400 | E18: =SUM(B18:D18) -> 260560
A19: Reduction vs Bhiwandi cost (%) | B19: =B18/B16 -> 0.17164179 | C19: =C18/C16 -> 0.14554054 | D19: =D18/D16 -> 0.12988651 | E19: =E18/E16 -> 0.14784385
A20: Saving per machine (₹) | B20: =B12-B13 -> 1150 | C20: =C12-C13 -> 1077 | D20: =D12-D13 -> 1030 | E20: =E18/E14 -> 1085.6667
A21: Saving per 20-machine load (₹) | B21: =B20*Inputs!$B$5 -> 23000 | C21: =C20*Inputs!$B$5 -> 21540 | D21: =D20*Inputs!$B$5 -> 20600 | E21: n/a
A24: Audit check vs supplied figures | B24: Goa | C24: Bengaluru | D24: Chennai | E24: Total
A25: Supplied Bhiwandi cost (₹) | B25: 536000 | C25: 592000 | D25: 634400 | E25: 1762400
A26: Supplied Kolhapur cost (₹) | B26: 444000 | C26: 505840 | D26: 552000 | E26: 1501840
A27: Supplied gross saving (₹) | B27: 92000 | C27: 86160 | D27: 82400 | E27: 260560
A28: Difference: model − supplied, Bhiwandi (₹) | B28: =B16-B25 -> 0 | C28: =C16-C25 -> 0 | D28: =D16-D25 -> 0 | E28: =E16-E25 -> 0
A29: Difference: model − supplied, Kolhapur (₹) | B29: =B17-B26 -> 0 | C29: =C17-C26 -> 0 | D29: =D17-D26 -> 0 | E29: =E17-E26 -> 0
A30: Difference: model − supplied, saving (₹) | B30: =B18-B27 -> 0 | C30: =C18-C27 -> 0 | D30: =D18-D27 -> 0 | E30: =E18-E27 -> 0
A31: Supplied combined reduction (%) | E31: 0.1479
A32: Difference: model − supplied (percentage points) | E32: =(E19-E31)*100 -> -0.0056150704
A34: All rupee differences are zero. The combined percentage differs by about 0.005 pp: 14.784% rounds to 14.78%, not 14.79%.

Sheet Components
A1: Cost-component analysis
A2: Saving attributable to each component. Last-mile is unchanged in the supplied model.
A3: Line | B3: Goa | C3: Bengaluru | D3: Chennai | E3: Total
A4: Primary saving per machine (₹) | B4: =Route_Model!B6-Route_Model!B7 -> 650 | C4: =Route_Model!C6-Route_Model!C7 -> 577 | D4: =Route_Model!D6-Route_Model!D7 -> 530 | E4: n/a
A5: Secondary saving per machine (₹) | B5: =Route_Model!B8-Route_Model!B9 -> 500 | C5: =Route_Model!C8-Route_Model!C9 -> 500 | D5: =Route_Model!D8-Route_Model!D9 -> 500 | E5: n/a
A6: Last-mile saving per machine (₹) | B6: =Route_Model!B10-Route_Model!B11 -> 0 | C6: =Route_Model!C10-Route_Model!C11 -> 0 | D6: =Route_Model!D10-Route_Model!D11 -> 0 | E6: n/a
A7: Total saving per machine (₹) | B7: =B4+B5+B6 -> 1150 | C7: =C4+C5+C6 -> 1077 | D7: =D4+D5+D6 -> 1030 | E7: =E11/Route_Model!E14 -> 1085.6667
A8: Primary saving, all machines (₹) | B8: =B4*Route_Model!B14 -> 52000 | C8: =C4*Route_Model!C14 -> 46160 | D8: =D4*Route_Model!D14 -> 42400 | E8: =SUM(B8:D8) -> 140560
A9: Secondary saving, all machines (₹) | B9: =B5*Route_Model!B14 -> 40000 | C9: =C5*Route_Model!C14 -> 40000 | D9: =D5*Route_Model!D14 -> 40000 | E9: =SUM(B9:D9) -> 120000
A10: Last-mile saving, all machines (₹) | B10: =B6*Route_Model!B14 -> 0 | C10: =C6*Route_Model!C14 -> 0 | D10: =D6*Route_Model!D14 -> 0 | E10: =SUM(B10:D10) -> 0
A11: Total saving (₹) | B11: =B8+B9+B10 -> 92000 | C11: =C8+C9+C10 -> 86160 | D11: =D8+D9+D10 -> 82400 | E11: =SUM(B11:D11) -> 260560
A12: Primary share of savings (%) | B12: =B8/B11 -> 0.56521739 | C12: =C8/C11 -> 0.53574745 | D12: =D8/D11 -> 0.51456311 | E12: =E8/E11 -> 0.53945348
A13: Secondary share of savings (%) | B13: =B9/B11 -> 0.43478261 | C13: =C9/C11 -> 0.46425255 | D13: =D9/D11 -> 0.48543689 | E13: =E9/E11 -> 0.46054652
A14: Last-mile share of savings (%) | B14: =B10/B11 -> 0 | C14: =C10/C11 -> 0 | D14: =D10/D11 -> 0 | E14: =E10/E11 -> 0
A15: Check: component total − Route_Model gross saving (₹) | E15: =E11-Route_Model!E18 -> 0
A17: Primary-rate headroom (calculated) | B17: Goa | C17: Bengaluru | D17: Chennai | E17: Note
A18: Kolhapur ₹/km at which primary cost per vehicle equals Bhiwandi | B18: =Route_Model!B4/Inputs!B8 -> 96 | C18: =Route_Model!C4/Inputs!C8 -> 60.31746 | D18: n/a | E18: Supplied Kolhapur rates are ₹44 and ₹42. Primary component only; Chennai has no supplied rate/distance.

Sheet Hub_Sensitivity
A1: Incremental Kolhapur hub-cost sensitivity
A2: Hub costs are ILLUSTRATIVE INPUTS (yellow). No actual V5 hub expense data are available.
A3: Baseline transportation cost – Bhiwandi (₹) | B3: =Route_Model!E16 -> 1762400
A4: Modelled gross transportation-cost saving (₹) | B4: =Route_Model!E18 -> 260560
A5: Break-even incremental hub cost (₹) | B5: =B4 -> 260560
A7: Incremental hub operating cost (₹) | B7: Net modelled benefit (₹) | C7: Net benefit (% of baseline cost) | D7: Modelled outcome
A8: 0 | B8: =$B$4-A8 -> 260560 | C8: =B8/$B$3 -> 0.14784385 | D8: =IF(B8>0,"Positive",IF(B8=0,"Break-even","Negative")) -> Positive
A9: 50000 | B9: =$B$4-A9 -> 210560 | C9: =B9/$B$3 -> 0.11947345 | D9: =IF(B9>0,"Positive",IF(B9=0,"Break-even","Negative")) -> Positive
A10: 100000 | B10: =$B$4-A10 -> 160560 | C10: =B10/$B$3 -> 0.091103041 | D10: =IF(B10>0,"Positive",IF(B10=0,"Break-even","Negative")) -> Positive
A11: 150000 | B11: =$B$4-A11 -> 110560 | C11: =B11/$B$3 -> 0.062732637 | D11: =IF(B11>0,"Positive",IF(B11=0,"Break-even","Negative")) -> Positive
A12: 200000 | B12: =$B$4-A12 -> 60560 | C12: =B12/$B$3 -> 0.034362233 | D12: =IF(B12>0,"Positive",IF(B12=0,"Break-even","Negative")) -> Positive
A13: 260560 | B13: =$B$4-A13 -> 0 | C13: =B13/$B$3 -> 0 | D13: =IF(B13>0,"Positive",IF(B13=0,"Break-even","Negative")) -> Break-even
A14: 300000 | B14: =$B$4-A14 -> -39440 | C14: =B14/$B$3 -> -0.022378575 | D14: =IF(B14>0,"Positive",IF(B14=0,"Break-even","Negative")) -> Negative
A17: Reverse-calculated planning hypothesis | B17: Target net benefit (% of baseline) | C17: Net modelled benefit (₹) | D17: Implied incremental hub cost (₹)
A18: Scenario A | B18: 0.05 | C18: =$B$3*B18 -> 88120 | D18: =$B$4-C18 -> 172440
A19: Scenario B | B19: 0.06 | C19: =$B$3*B19 -> 105744 | D19: =$B$4-C19 -> 154816
A21: Net modelled benefit = gross saving − incremental hub cost. Net % = net ÷ baseline transportation cost (not a profit margin). Scenarios A/B show the hub cost that WOULD be implied by a 5–6% net benefit; they are not actual expenses or results.

Sheet Dashboard
A1: Executive dashboard (modelled)
A2: All cells link to model sheets. Modelled gross savings; not verified realised savings.
A3: Metric | B3: Value
A4: Baseline transportation cost – Bhiwandi (₹) | B4: =Route_Model!E16 -> 1762400
A5: Proposed transportation cost – Kolhapur (₹) | B5: =Route_Model!E17 -> 1501840
A6: Modelled gross saving (₹) | B6: =Route_Model!E18 -> 260560
A7: Gross reduction (%) | B7: =Route_Model!E19 -> 0.14784385
A8: Average saving per machine (₹) | B8: =Route_Model!E20 -> 1085.6667
A9: Machines modelled (3 routes) | B9: =Route_Model!E14 -> 240
A10: Vehicle loads modelled | B10: =Route_Model!E15 -> 12
A11: Break-even incremental hub cost (₹) | B11: =Hub_Sensitivity!B5 -> 260560
A12: Implied hub cost at 5% net benefit (₹) | B12: =Hub_Sensitivity!D18 -> 172440
A13: Implied hub cost at 6% net benefit (₹) | B13: =Hub_Sensitivity!D19 -> 154816
A16: Route | B16: Gross saving (₹) | C16: Reduction (%) | D16: Saving per machine (₹)
A17: Goa | B17: =Route_Model!B18 -> 92000 | C17: =Route_Model!B19 -> 0.17164179 | D17: =Route_Model!B20 -> 1150
A18: Bengaluru | B18: =Route_Model!C18 -> 86160 | C18: =Route_Model!C19 -> 0.14554054 | D18: =Route_Model!C20 -> 1077
A19: Chennai | B19: =Route_Model!D18 -> 82400 | C19: =Route_Model!D19 -> 0.12988651 | D19: =Route_Model!D20 -> 1030

Sheet Notes
A1: Assumptions, limitations and data notes
A3: Modelling basis | B3: 80 machines per route (4 loads of 20) is the supplied modelling basis, not actual shipment volume. Totals of 240 machines and 12 loads are sums of that assumption.
A4: Cost distances | B4: Cost distances differ from the transit-time report (e.g. Goa–Kolhapur 250 km here vs 223 km there; Bengaluru 1,000/630 km vs 1,002/631 km). Supplied cost distances are used as instructed.
A5: Chennai inputs | B5: Primary cost per vehicle (₹48,600 / ₹38,000) are working figures pending confirmation. No rate or distance has been inferred. The Kolhapur figure equals the Bengaluru Bhiwandi vehicle cost; verify it is not a transcription error.
A6: Uniform secondary rates | B6: Secondary cost is a flat ₹3,000 (Bhiwandi) and ₹2,500 (Kolhapur) per machine on every route, giving a ₹500 saving per machine that accounts for 46.05% of total modelled savings. Destination-specific rates should be confirmed.
A7: Destination mix | B7: The model assumes all 80 machines per route are served from the Kolhapur catchment. Destinations in the Bhiwandi catchment (e.g. Pune, Nagpur) would not show this saving.
A8: Last-mile | B8: Unchanged at ₹2,500 per machine in both scenarios; contributes nothing to modelled savings.
A9: Hub costs | B9: Incremental Kolhapur hub costs (rent, utilities, labour, handling, security, administration, extra transfers) are unavailable and not estimated. Sensitivity values are illustrative.
A10: Rounding audit | B10: Combined reduction is 14.784%, shown as 14.78%. The brief's 14.79% is a rounding slip; rupee figures all reconcile.
A11: Not attributable | B11: Savings are not attributed to fuel efficiency, driver productivity, utilisation or procurement; no supporting data exist.
